game_of_life/__init__.py
game_of_life/controller.py
game_of_life/game.py
game_of_life/run.py
game_of_life/.data/__init__.py
game_of_life/.data/beacon
game_of_life/.data/bee_hive
game_of_life/.data/blinker
game_of_life/.data/block
game_of_life/.data/boat
game_of_life/.data/diehard
game_of_life/.data/glider
game_of_life/.data/glider__
game_of_life/.data/gosper_glider_gun
game_of_life/.data/loaf
game_of_life/.data/pulsar
game_of_life/.data/r_pentomino
game_of_life/.data/toad
game_of_life/.data/tub
tests/__init__.py
tests/controller_test.py
tests/game_test.py
game_of_life_M-0.0.2.dist-info/METADATA
game_of_life_M-0.0.2.dist-info/WHEEL
game_of_life_M-0.0.2.dist-info/top_level.txt
game_of_life_M-0.0.2.dist-info/RECORD
