Metadata-Version: 2.1
Name: game-of-life-M
Version: 0.0.2
Summary: Conway's game of life in python
Home-page: https://github.com/hogum/game-of-life
Author: mugoh
Author-email: mugoh.ks@gmail.com
License: UNKNOWN
Platform: UNKNOWN
Classifier: Programming Language :: Python :: 3
Classifier: License :: OSI Approved :: MIT License
Classifier: Operating System :: OS Independent
Requires-Python: >=3.7
Requires-Dist: numpy
